diskimgr/__init__.py
diskimgr/__main__.py
diskimgr/config.py
diskimgr/configure.py
diskimgr/disk.py
diskimgr/diskimgr.py
diskimgr/gui.py
diskimgr/shared.py
diskimgr/wrappers.py
diskimgr/icons/diskimgr.png
diskimgr-0.2.0.dist-info/LICENSE
diskimgr-0.2.0.dist-info/METADATA
diskimgr-0.2.0.dist-info/WHEEL
diskimgr-0.2.0.dist-info/entry_points.txt
diskimgr-0.2.0.dist-info/top_level.txt
diskimgr-0.2.0.dist-info/RECORD
